Metadata-Version: 2.1
Name: pcla-elo
Version: 0.0.1
Summary: Implementation of the ELO Algorithm
Home-page: https://pcla.wiki/
Author: Michael Mogessie
Author-email: mogessie@upenn.edu
Keywords: python,elo
Classifier: Development Status :: 3 - Alpha
Classifier: Intended Audience :: Education
Classifier: Programming Language :: Python :: 2
Classifier: Programming Language :: Python :: 3
Classifier: Operating System :: MacOS :: MacOS X
Classifier: Operating System :: Microsoft :: Windows
License-File: LICENSE
